hypereditor/__init__.py
hypereditor/admin.py
hypereditor/apps.py
hypereditor/field.py
hypereditor/fields.py
hypereditor/hyper_blocks.py
hypereditor/models.py
hypereditor/settings.py
hypereditor/tests.py
hypereditor/urls.py
hypereditor/utils.py
hypereditor/views.py
hypereditor/__pycache__/__init__.cpython-36.pyc
hypereditor/__pycache__/admin.cpython-36.pyc
hypereditor/__pycache__/apps.cpython-36.pyc
hypereditor/__pycache__/fields.cpython-36.pyc
hypereditor/__pycache__/hyper_blocks.cpython-36.pyc
hypereditor/__pycache__/models.cpython-36.pyc
hypereditor/__pycache__/settings.cpython-36.pyc
hypereditor/__pycache__/tests.cpython-36.pyc
hypereditor/__pycache__/urls.cpython-36.pyc
hypereditor/__pycache__/utils.cpython-36.pyc
hypereditor/__pycache__/views.cpython-36.pyc
hypereditor/blocks/__init__.py
hypereditor/blocks/base.py
hypereditor/blocks/__pycache__/__init__.cpython-36.pyc
hypereditor/blocks/__pycache__/base.cpython-36.pyc
hypereditor/migrations/__init__.py
hypereditor/migrations/__pycache__/__init__.cpython-36.pyc
hypereditor/static/hypereditor/hyper_editor.css
hypereditor/static/hypereditor/hyper_editor.js
hypereditor/templates/hypereditor/hyper_editor.html
hypereditor/templates/hypereditor/preview.html
hypereditor/templates/hypereditor/blocks/column/default.html
hypereditor/templates/hypereditor/blocks/contentbox/default.html
hypereditor/templates/hypereditor/blocks/heading/default.html
hypereditor/templates/hypereditor/blocks/image/default.html
hypereditor/templates/hypereditor/blocks/link/default.html
hypereditor/templates/hypereditor/blocks/row/default.html
hypereditor/templates/hypereditor/blocks/section/default.html
hypereditor/templates/hypereditor/blocks/slider/default.html
hypereditor/templates/hypereditor/blocks/tab/default.html
hypereditor/templates/hypereditor/blocks/text/default.html
hypereditor/templates/hypereditor/edit_handlers/hyper_editor_field_panel.html
hypereditor/templates/hypereditor/js/blocks.js
hypereditor-0.1.0.dist-info/LICENSE
hypereditor-0.1.0.dist-info/METADATA
hypereditor-0.1.0.dist-info/WHEEL
hypereditor-0.1.0.dist-info/top_level.txt
hypereditor-0.1.0.dist-info/RECORD
