Metadata-Version: 2.1
Name: hypereditor
Version: 0.1.0
Summary: Hyper Editor Integration With Django
Home-page: UNKNOWN
Author: Shimul Chowdhury
Author-email: shimul@divine-it.net
License: MIT
Platform: UNKNOWN
Classifier: Environment :: Web Environment
Classifier: Intended Audience :: Developers
Classifier: Operating System :: OS Independent
Classifier: Programming Language :: Python
Classifier: Programming Language :: Python :: 3
Classifier: Programming Language :: Python :: 3.4
Classifier: Programming Language :: Python :: 3.5
Classifier: Programming Language :: Python :: 3.6
Classifier: Programming Language :: Python :: 3.7
Classifier: Framework :: Django
Classifier: Framework :: Django :: 2.0
Classifier: Framework :: Django :: 2.1
Classifier: Framework :: Django :: 2.2
Requires-Dist: Django (<2.3,>=1.11)
